{
    "uid": "a3a0971d-c46b-46ec-82b8-69b859c00c0b",
    "name": "52_ExtraTrees",
    "preprocessing": [
        {
            "remove_columns": [
                "feature_48",
                "feature_49",
                "feature_50"
            ],
            "ml_task": "binary_classification",
            "params": {
                "columns_preprocessing": {
                    "feature_48": [
                        "remove_column"
                    ],
                    "feature_49": [
                        "remove_column"
                    ],
                    "feature_50": [
                        "remove_column"
                    ]
                },
                "target_preprocessing": [
                    "na_exclude"
                ],
                "ml_task": "binary_classification"
            }
        }
    ],
    "learners": [
        {
            "library_version": "0.24.1",
            "algorithm_name": "Extra Trees Classifier",
            "algorithm_short_name": "Extra Trees",
            "uid": "ba6cb34a-2d65-419a-b099-de42612e682f",
            "params": {
                "model_type": "Extra Trees",
                "ml_task": "binary_classification",
                "n_jobs": -1,
                "seed": 1239,
                "criterion": "gini",
                "max_features": 0.7,
                "min_samples_split": 50,
                "max_depth": 3,
                "explain_level": 0
            },
            "name": "learner_fold_0"
        }
    ],
    "params": {
        "additional": {
            "trees_in_step": 100,
            "max_steps": 50,
            "early_stopping_rounds": 50,
            "max_rows_limit": null,
            "max_cols_limit": null
        },
        "preprocessing": {
            "columns_preprocessing": {
                "feature_48": [
                    "remove_column"
                ],
                "feature_49": [
                    "remove_column"
                ],
                "feature_50": [
                    "remove_column"
                ]
            },
            "target_preprocessing": [
                "na_exclude"
            ],
            "ml_task": "binary_classification"
        },
        "validation_strategy": {
            "validation_type": "split",
            "train_ratio": 0.9,
            "shuffle": true,
            "stratify": true,
            "X_path": "AutoML_3/X.parquet",
            "y_path": "AutoML_3/y.parquet",
            "results_path": "AutoML_3"
        },
        "learner": {
            "model_type": "Extra Trees",
            "ml_task": "binary_classification",
            "n_jobs": -1,
            "seed": 1239,
            "criterion": "gini",
            "max_features": 0.7,
            "min_samples_split": 50,
            "max_depth": 3,
            "explain_level": 0
        },
        "ml_task": "binary_classification",
        "explain_level": 0,
        "name": "52_ExtraTrees",
        "status": "initialized",
        "final_loss": null,
        "train_time": null,
        "max_time_for_learner": 60
    },
    "saved": [
        "52_ExtraTrees/learner_fold_0.extra_trees"
    ],
    "predictions_fname": "52_ExtraTrees/predictions_validation.csv",
    "metric_name": "logloss",
    "final_loss": 0.6018387572156958,
    "train_time": 1.9379489421844482,
    "is_stacked": false,
    "threshold": 0.3329629436733247
}